README
setup.py
etc/txlongpoll.yaml
twisted/plugins/txlongpoll.py
txlongpoll/__init__.py
txlongpoll/client.py
txlongpoll/frontend.py
txlongpoll/plugin.py
txlongpoll/services.py
txlongpoll.egg-info/PKG-INFO
txlongpoll.egg-info/SOURCES.txt
txlongpoll.egg-info/dependency_links.txt
txlongpoll.egg-info/not-zip-safe
txlongpoll.egg-info/requires.txt
txlongpoll.egg-info/top_level.txt
txlongpoll/specs/amqp0-8.xml
txlongpoll/testing/__init__.py
txlongpoll/testing/client.py
txlongpoll/tests/__init__.py
txlongpoll/tests/test_client.py
txlongpoll/tests/test_frontend.py
txlongpoll/tests/test_plugin.py
txlongpoll/tests/test_services.py