Metadata-Version: 1.0
Name: txlongpoll
Version: 0.3.2
Summary: Long polling HTTP frontend for AMQP
Home-page: UNKNOWN
Author: UNKNOWN
Author-email: UNKNOWN
License: UNKNOWN
Platform: UNKNOWN
